_HyPhy.cpython-35m-darwin.so
HyPhy/__init__.py
HyPhy-0.1.3.dist-info/DESCRIPTION.rst
HyPhy-0.1.3.dist-info/METADATA
HyPhy-0.1.3.dist-info/RECORD
HyPhy-0.1.3.dist-info/WHEEL
HyPhy-0.1.3.dist-info/metadata.json
HyPhy-0.1.3.dist-info/top_level.txt
