Metadata-Version: 2.0
Name: HyPhy
Version: 0.1.3
Summary: HyPhy package interface library
Home-page: http://github.com/veg/hyphy
Author: Sergei L Kosakovsky Pond and Steven Weaver
Author-email: spond@temple.edu
License: UNKNOWN
Platform: UNKNOWN
